sudachipy/sudachipy.cpython-310-darwin.so
sudachipy/config.py
sudachipy/command_line.py
sudachipy/__init__.py
sudachipy/sudachipy.pyi
sudachipy/errors.py
sudachipy/tokenizer/__init__.py
sudachipy/resources/rewrite.def
sudachipy/resources/unk.def
sudachipy/resources/sudachi.json
sudachipy/resources/char.def
sudachipy/morphemelist/__init__.py
sudachipy/morpheme/__init__.py
sudachipy/dictionary/__init__.py
SudachiPy-0.6.10.dist-info/RECORD
SudachiPy-0.6.10.dist-info/WHEEL
SudachiPy-0.6.10.dist-info/entry_points.txt
SudachiPy-0.6.10.dist-info/top_level.txt
SudachiPy-0.6.10.dist-info/METADATA
