Metadata-Version: 2.2
Name: SudachiPy
Version: 0.6.10
Summary: Python version of Sudachi, the Japanese Morphological Analyzer
Home-page: https://github.com/WorksApplications/sudachi.rs/tree/develop/python
Author: Works Applications
Author-email: sudachi@worksap.co.jp
License: Apache-2.0
Provides-Extra: tests
Requires-Dist: tokenizers; extra == "tests"
Requires-Dist: sudachidict_core; extra == "tests"
Dynamic: author
Dynamic: author-email
Dynamic: description
Dynamic: description-content-type
Dynamic: home-page
Dynamic: license
Dynamic: provides-extra
Dynamic: summary
